<annotation><filename>.\Annotated_files\202_0088.jpg</filename><user>Krishna</user><curve><curve_name>ellipse1</curve_name><pt><x>151.7991</x><y>139.369</y></pt><pt><x>142.0087</x><y>123.9105</y></pt><pt><x>134.7948</x><y>100.7227</y></pt><pt><x>132.7336</x><y>82.1725</y></pt><pt><x>137.8865</x><y>64.6528</y></pt><pt><x>145.6157</x><y>51.2555</y></pt><pt><x>157.4672</x><y>50.2249</y></pt><pt><x>170.8646</x><y>56.4083</y></pt><pt><x>184.262</x><y>67.2293</y></pt><pt><x>193.0218</x><y>82.6878</y></pt><pt><x>197.6594</x><y>102.2686</y></pt><pt><x>199.7205</x><y>120.3035</y></pt><pt><x>198.1747</x><y>138.3384</y></pt><pt><x>191.476</x><y>149.6747</y></pt><pt><x>183.7467</x><y>154.8275</y></pt><pt><x>167.2576</x><y>153.7969</y></pt><pt><x>151.7991</x><y>139.369</y></pt><ellipse_data><semimajor>54.8006</semimajor><semiminor>30.7574</semiminor><x0>166.825</x0><y0>102.6908</y0><Phi>1.2722</Phi></ellipse_data></curve><curve><curve_name>ellipse2</curve_name><pt><x>143.0393</x><y>29.6135</y></pt><pt><x>157.4672</x><y>30.6441</y></pt><pt><x>176.0175</x><y>39.4039</y></pt><pt><x>190.4454</x><y>53.8319</y></pt><pt><x>202.8122</x><y>73.9279</y></pt><pt><x>208.4803</x><y>91.9629</y></pt><pt><x>212.0873</x><y>112.5742</y></pt><pt><x>213.1179</x><y>133.1856</y></pt><pt><x>210.0262</x><y>151.7358</y></pt><pt><x>202.8122</x><y>166.679</y></pt><pt><x>191.9913</x><y>178.0153</y></pt><pt><x>169.3188</x><y>182.6528</y></pt><pt><x>150.2533</x><y>178.0153</y></pt><pt><x>132.7336</x><y>164.6179</y></pt><pt><x>119.3362</x><y>147.6135</y></pt><pt><x>109.5459</x><y>124.4258</y></pt><pt><x>104.393</x><y>87.3253</y></pt><pt><x>109.0306</x><y>57.9541</y></pt><pt><x>122.9432</x><y>36.8275</y></pt><pt><x>143.0393</x><y>29.6135</y></pt><ellipse_data><semimajor>79.3465</semimajor><semiminor>52.307</semiminor><x0>158.7896</x0><y0>106.3825</y0><Phi>1.287</Phi></ellipse_data></curve><curve><curve_name>ellipse3</curve_name><pt><x>46.6812</x><y>154.8275</y></pt><pt><x>51.8341</x><y>157.4039</y></pt><pt><x>53.8952</x><y>166.679</y></pt><pt><x>52.8646</x><y>173.893</y></pt><pt><x>46.6812</x><y>180.0764</y></pt><pt><x>40.4978</x><y>179.0459</y></pt><pt><x>36.3755</x><y>171.3166</y></pt><pt><x>36.8908</x><y>163.5873</y></pt><pt><x>41.0131</x><y>157.9192</y></pt><pt><x>46.6812</x><y>154.8275</y></pt><ellipse_data><semimajor>12.8814</semimajor><semiminor>8.8854</semiminor><x0>45.2917</x0><y0>167.7</y0><Phi>1.7357</Phi></ellipse_data></curve><curve><curve_name>ellipse4</curve_name><pt><x>165.1965</x><y>93.5087</y></pt><pt><x>169.3188</x><y>95.0546</y></pt><pt><x>172.4105</x><y>102.2686</y></pt><pt><x>171.3799</x><y>109.9978</y></pt><pt><x>165.1965</x><y>111.0284</y></pt><pt><x>161.0742</x><y>105.8755</y></pt><pt><x>161.0742</x><y>98.1463</y></pt><pt><x>165.1965</x><y>93.5087</y></pt><ellipse_data><semimajor>9.3535</semimajor><semiminor>5.958</semiminor><x0>166.617</x0><y0>102.7661</y0><Phi>1.3968</Phi></ellipse_data></curve></annotation>